AUTHORS
ChangeLog
LICENSE
MANIFEST.in
README.rst
requirements.txt
run_tests.sh
setup.cfg
setup.py
test-requirements.txt
tox.ini
cognosco/__init__.py
cognosco/audit.py
cognosco/exc.py
cognosco/github_util.py
cognosco/reports.py
cognosco/repository.py
cognosco.egg-info/PKG-INFO
cognosco.egg-info/SOURCES.txt
cognosco.egg-info/dependency_links.txt
cognosco.egg-info/entry_points.txt
cognosco.egg-info/not-zip-safe
cognosco.egg-info/requires.txt
cognosco.egg-info/top_level.txt
tests/__init__.py
tests/unit/__init__.py
tests/unit/test_audit.py
tests/unit/test_exc.py
tests/unit/test_github_util.py
tests/unit/test_reports.py
tests/unit/test_repository.py