Metadata-Version: 1.1
Name: cognosco
Version: 0.1.0
Summary: Audit Merged Pull Requests
Home-page: https://github.com/klmitch/cognosco
Author: Kevin L. Mitchell
Author-email: kevin.mitchell@rackspace.com
License: UNKNOWN
Platform: UNKNOWN
Classifier: Development Status :: 3 - Alpha
Classifier: Environment :: Console
Classifier: License :: OSI Approved :: Apache Software License
Classifier: Programming Language :: Python
Classifier: Programming Language :: Python :: 2
Classifier: Programming Language :: Python :: 2.6
Classifier: Programming Language :: Python :: 2.7
Classifier: Programming Language :: Python :: 3
Classifier: Programming Language :: Python :: 3.3
Classifier: Programming Language :: Python :: 3.4
